pynca/__init__.py
pynca/practice.py
pynca/tools.py
pynca-1.2.3.dist-info/LICENSE
pynca-1.2.3.dist-info/METADATA
pynca-1.2.3.dist-info/WHEEL
pynca-1.2.3.dist-info/top_level.txt
pynca-1.2.3.dist-info/RECORD
