Metadata-Version: 2.1
Name: pynca
Version: 1.2.3
Summary: The tools for Non-compartmental Analysis of pharmacometrix
Home-page: https://github.com/onewquant/pynca
Author: Onew
Author-email: seunghwan0216@gmail.com
License: UNKNOWN
Download-URL: https://github.com/Onewquant/pynca/archive/master.zip
Keywords: pynca,PyNCA
Platform: UNKNOWN
Classifier: Programming Language :: Python :: 3
Classifier: Programming Language :: Python :: 3.2
Classifier: Programming Language :: Python :: 3.3
Classifier: Programming Language :: Python :: 3.4
Classifier: Programming Language :: Python :: 3.5
Classifier: Programming Language :: Python :: 3.6
Classifier: Programming Language :: Python :: 3.7
Classifier: Programming Language :: Python :: 3.8
Classifier: Programming Language :: Python :: 3.9
Classifier: Programming Language :: Python :: 3.10
Classifier: Programming Language :: Python :: 3.11
Classifier: Programming Language :: Python :: 3.12
Requires-Python: >=3
Requires-Dist: matplotlib
Requires-Dist: numpy
Requires-Dist: openpyxl
Requires-Dist: pandas
Requires-Dist: xlrd
Requires-Dist: scipy
Requires-Dist: seaborn
